wsqr/__init__.py
wsqr/main.py
wsqr-0.1.7.dist-info/METADATA
wsqr-0.1.7.dist-info/WHEEL
wsqr-0.1.7.dist-info/entry_points.txt
wsqr-0.1.7.dist-info/top_level.txt
wsqr-0.1.7.dist-info/RECORD
