Metadata-Version: 2.4
Name: wsqr
Version: 0.1.7
Summary: Advanced QR Code Decoder Tool
Home-page: https://github.com/twfb/wsqr
Author: twfb
Author-email: 
License: GPLv3
Requires-Python: >=3.7
Requires-Dist: typer
Requires-Dist: rich
Requires-Dist: opencv-python-headless
Requires-Dist: numpy
Requires-Dist: psutil
Requires-Dist: pyzbar
Requires-Dist: zxing-cpp
Requires-Dist: qreader
Requires-Dist: requests
Dynamic: author
Dynamic: description
Dynamic: description-content-type
Dynamic: home-page
Dynamic: license
Dynamic: requires-dist
Dynamic: requires-python
Dynamic: summary
